politicalplaces/__init__.py
politicalplaces/admin.py
politicalplaces/apps.py
politicalplaces/exceptions.py
politicalplaces/fields.py
politicalplaces/models.py
politicalplaces/tests.py
politicalplaces/utils.py
politicalplaces/widgets.py
politicalplaces/backends/__init__.py
politicalplaces/backends/googlemaps.py
politicalplaces/management/__init__.py
politicalplaces/management/commands/__init__.py
politicalplaces/management/commands/refresh_data.py
politicalplaces/migrations/0001_initial.py
politicalplaces/migrations/0002_auto_20170114_1147.py
politicalplaces/migrations/0003_auto_20170116_0958.py
politicalplaces/migrations/0004_politicalplace_continent.py
politicalplaces/migrations/0005_auto_20170119_1737.py
politicalplaces/migrations/0006_mapitem_parent.py
politicalplaces/migrations/0007_auto_20170315_1728.py
politicalplaces/migrations/0008_auto_20170317_1636.py
politicalplaces/migrations/0009_politicalplace_postal_code.py
politicalplaces/migrations/0010_politicalplace_self_item.py
politicalplaces/migrations/0011_mapitem_error_log.py
politicalplaces/migrations/0012_auto_20170720_1350.py
politicalplaces/migrations/__init__.py
politicalplaces/static/politicalplaces/css/politicalplaces.css
politicalplaces/static/politicalplaces/img/searchplace.png
politicalplaces/static/politicalplaces/js/politicalplaces.js
politicalplaces/static/politicalplaces/js/politicalplaces_old.js
politicalplaces/templates/place_field/place_widget.html
django_political_map-1.2.2.dist-info/LICENSE
django_political_map-1.2.2.dist-info/METADATA
django_political_map-1.2.2.dist-info/WHEEL
django_political_map-1.2.2.dist-info/top_level.txt
django_political_map-1.2.2.dist-info/RECORD
