Metadata-Version: 2.1
Name: django-political-map
Version: 1.2.2
Summary: Django application to store geolocalized places and organize them according to political hierarchy.
Home-page: https://github.com/20tab/django-political-map
Author: 20tab srl
Author-email: info@20tab.com
License: UNKNOWN
Project-URL: Bug Tracker, https://github.com/20tab/django-political-map/issues
Platform: UNKNOWN
Classifier: Programming Language :: Python :: 3
Classifier: License :: OSI Approved :: MIT License
Classifier: Operating System :: OS Independent
Requires-Python: >=2.7
License-File: LICENSE
Requires-Dist: googlemaps (==3.0.2)
